[
  {
    "id": "tribusUrbanas",
    "img": "./books/tribusUrbanasTapa.png",
    "title": "Tribus Urbanas",
    "desc": ""
  },
  {
    "id": "tonosYToneles",
    "img": "./books/tonosYTonelesTapa.png",
    "title": "Tonos y Toneles",
    "desc": ""
  },
  {
    "id": "laMemoriaDeLosBoliches",
    "img": "./books/laMemoriaDeLosBolichesTapa.png",
    "title": "La memoria de los boliches",
    "desc": ""
  },
  {
    "id": "bares",
    "img": "./books/baresTapa.png",
    "title": "Bares",
    "desc": ""
  },
  {
    "id": "apuntesDeUnPataIPerro",
    "img": "./books/apuntesDeUnPataIPerroTapa.png",
    "title": "Apuntes de un pata i' perro",
    "desc": ""
  },
  {
    "id": "quieroQueEntiendas",
    "img": "./books/quieroQueEntiendasTapa.png",
    "title": "Quiero que entiendas",
    "desc": ""
  }
]
